imessage_reader/__init__.py
imessage_reader/cli.py
imessage_reader/common.py
imessage_reader/create_sqlite.py
imessage_reader/data_container.py
imessage_reader/fetch_data.py
imessage_reader/info.py
imessage_reader/write_excel.py
imessage_reader-0.6.1.dist-info/LICENSE
imessage_reader-0.6.1.dist-info/METADATA
imessage_reader-0.6.1.dist-info/WHEEL
imessage_reader-0.6.1.dist-info/entry_points.txt
imessage_reader-0.6.1.dist-info/top_level.txt
imessage_reader-0.6.1.dist-info/RECORD
