Metadata-Version: 2.1
Name: imessage_reader
Version: 0.6.1
Summary: Fetch recipients and chat messages from the chat.db database.
Home-page: https://github.com/niftycode/imessage_reader
Author: Bodo Schönfeld
Author-email: bodo.schoenfeld@niftycode.de
License: MIT
Classifier: License :: OSI Approved :: MIT License
Classifier: Operating System :: MacOS
Classifier: Operating System :: POSIX :: Linux
Classifier: Programming Language :: Python :: 3
Classifier: Programming Language :: Python :: 3.9
Classifier: Programming Language :: Python :: 3.10
Classifier: Programming Language :: Python :: 3.11
Requires-Python: >=3.8
License-File: LICENSE
